mdformat_black/__init__.py
mdformat_black-0.1.1.dist-info/entry_points.txt
mdformat_black-0.1.1.dist-info/LICENSE
mdformat_black-0.1.1.dist-info/WHEEL
mdformat_black-0.1.1.dist-info/METADATA
mdformat_black-0.1.1.dist-info/RECORD
