Metadata-Version: 2.1
Name: mdformat-black
Version: 0.1.1
Summary: Mdformat plugin to Blacken Python code blocks
Home-page: https://github.com/hukkinj1/mdformat-black
License: MIT
Keywords: mdformat,markdown,commonmark,formatter
Author: Taneli Hukkinen
Author-email: hukkinj1@users.noreply.github.com
Requires-Python: >=3.6,<4.0
Classifier: License :: OSI Approved :: MIT License
Classifier: Programming Language :: Python :: 3
Classifier: Programming Language :: Python :: 3.6
Classifier: Programming Language :: Python :: 3.7
Classifier: Programming Language :: Python :: 3.8
Classifier: Topic :: Documentation
Classifier: Topic :: Text Processing :: Markup
Classifier: Typing :: Typed
Requires-Dist: black
Requires-Dist: mdformat (>=0.3.0)
Project-URL: Repository, https://github.com/hukkinj1/mdformat-black
